README.rst
setup.py
./fammer.py
./tmalign.py
fammer.egg-info/PKG-INFO
fammer.egg-info/SOURCES.txt
fammer.egg-info/dependency_links.txt
fammer.egg-info/requires.txt
fammer.egg-info/top_level.txt
fammerlib/__init__.py
fammerlib/_share.py
fammerlib/add.py
fammerlib/build.py
fammerlib/cluster.py
fammerlib/refine.py
fammerlib/scan.py
fammerlib/tasks.py
fammerlib/tmalign.py
fammerlib/update_fasta.py