Metadata-Version: 1.1
Name: fammer
Version: 0.2
Summary: Fammer: Tools for protein superfamily sequence profile alignment and curation.
Home-page: http://github.com/etal/fammer
Author: Eric Talevich
Author-email: eric.talevich@gmail.com
License: UNKNOWN
Platform: UNKNOWN
Classifier: Development Status :: 3 - Alpha
Classifier: Intended Audience :: Science/Research
Classifier: License :: OSI Approved :: BSD License
Classifier: Programming Language :: Python :: 2.7
Classifier: Programming Language :: Python :: Implementation :: PyPy
Classifier: Topic :: Scientific/Engineering :: Bio-Informatics
